megawidget/__init__.py
megawidget/__main__.py
megawidget/choice.py
megawidget/confirm.py
megawidget/pathentry.py
megawidget/scrollbox.py
megawidget/table.py
megawidget/toast.py
megawidget/tree.py
megawidget/choice/__init__.py
megawidget/confirmation/__init__.py
megawidget/error/__init__.py
megawidget/hooking/__init__.py
megawidget/hooking/ante_build_hook.py
megawidget/hooking/ante_release_hook.py
megawidget/hooking/post_build_hook.py
megawidget/hooking/post_release_hook.py
megawidget/notes/tk_frame_public_and_protected_attributes.txt
megawidget/notes/tk_toplevel_public_and_protected_attributes.txt
megawidget/pathfield/__init__.py
megawidget/pyrustic_data/hooking.json
megawidget/pyrustic_data/hubstore.json
megawidget/pyrustic_data/release_info.json
megawidget/pyrustic_data/backstage/config/build.json
megawidget/pyrustic_data/backstage/config/init.json
megawidget/pyrustic_data/backstage/config/release.json
megawidget/pyrustic_data/backstage/data/build_report.json
megawidget/pyrustic_data/backstage/data/github_release_form.json
megawidget/pyrustic_data/backstage/hooking/build.json
megawidget/pyrustic_data/backstage/hooking/init.json
megawidget/pyrustic_data/backstage/hooking/release.json
megawidget/pyrustic_data/backstage/report/build_report.json
megawidget/pyrustic_data/backstage/report/release_report.json
megawidget/pyrustic_data/hubstore/img.json
megawidget/pyrustic_data/hubstore/promotion.json
megawidget/scrollbox/__init__.py
megawidget/table/__init__.py
megawidget/toast/__init__.py
megawidget/tree/__init__.py
secret/SCRATCH.py
secret/__init__.py
tests/__init__.py
tests/__main__.py
megawidget-0.0.6.dist-info/LICENSE
megawidget-0.0.6.dist-info/METADATA
megawidget-0.0.6.dist-info/WHEEL
megawidget-0.0.6.dist-info/entry_points.txt
megawidget-0.0.6.dist-info/top_level.txt
megawidget-0.0.6.dist-info/RECORD
