Metadata-Version: 2.1
Name: megawidget
Version: 0.0.6
Summary: Collection of megawidgets to build GUIs with Python
Home-page: https://github.com/pyrustic/megawidget
Author: Pyrustic Evangelist
Author-email: rusticalex@yahoo.com
Maintainer: Pyrustic Evangelist
Maintainer-email: rusticalex@yahoo.com
License: MIT
Keywords: megawidgets,tkinter,gui,collection,desktop-application,widget-collection,pyrustic,frontend
Platform: UNKNOWN
Classifier: Programming Language :: Python :: 3
Classifier: License :: OSI Approved :: MIT License
Classifier: Operating System :: OS Independent
Requires-Python: >=3.5
License-File: LICENSE
Requires-Dist: viewable
Requires-Dist: tkutil
